colordove_auto/__init__.py
colordove_auto/env.py
colordove_auto/main.py
colordove_auto/mitmdump.py
colordove_auto/run.py
colordove_auto/command/__init__.py
colordove_auto/command/alibaba/__init__.py
colordove_auto/command/alibaba/supplier/Order.py
colordove_auto/command/alibaba/supplier/__init__.py
colordove_auto/command/alibaba/supplier/service/OrderService.py
colordove_auto/command/alibaba/supplier/service/ProductService.py
colordove_auto/command/alibaba/supplier/service/__init__.py
colordove_auto/command/test/Index.py
colordove_auto/command/test/__init__.py
colordove_auto/command/tiktok/__init__.py
colordove_auto/command/tiktok/bill/__init__.py
colordove_auto/command/tiktok/bill/service/BillService.py
colordove_auto/command/tiktok/bill/service/__init__.py
colordove_auto/command/tiktok/logistics/__init__.py
colordove_auto/command/tiktok/logistics/service/LogisticsService.py
colordove_auto/command/tiktok/logistics/service/__init__.py
colordove_auto/command/tiktok/order/__init__.py
colordove_auto/command/tiktok/order/service/OrderService.py
colordove_auto/command/tiktok/order/service/__init__.py
colordove_auto/command/tiktok/product/__init__.py
colordove_auto/command/tiktok/product/service/OptimizerService.py
colordove_auto/command/tiktok/product/service/ProductService.py
colordove_auto/command/tiktok/product/service/__init__.py
colordove_auto/command/tiktok/shop/__init__.py
colordove_auto/command/tiktok/shop/service/ShopService.py
colordove_auto/command/tiktok/shop/service/__init__.py
colordove_auto/command/tiktok/union/__init__.py
colordove_auto/command/tiktok/union/service/UnionService.py
colordove_auto/command/tiktok/union/service/__init__.py
colordove_auto/common/Common.py
colordove_auto/common/__init__.py
colordove_auto/common/api/__init__.py
colordove_auto/common/api/alibaba/AlibabaApi.py
colordove_auto/common/api/alibaba/__init__.py
colordove_auto/common/api/tiktok/BillApi.py
colordove_auto/common/api/tiktok/LogisticsApi.py
colordove_auto-1.0.57.dist-info/LICENSE
colordove_auto-1.0.57.dist-info/METADATA
colordove_auto-1.0.57.dist-info/WHEEL
colordove_auto-1.0.57.dist-info/entry_points.txt
colordove_auto-1.0.57.dist-info/top_level.txt
colordove_auto-1.0.57.dist-info/RECORD
