Metadata-Version: 2.1
Name: colordove_auto
Version: 1.0.57
Summary: Cross border e-commerce automation program
Home-page: https://www.colordove.com
Author: Zhongshuizhou
Author-email: zhongshuizhou@qq.com
Classifier: Programming Language :: Python :: 3.8
Classifier: License :: OSI Approved :: MIT License
Classifier: Operating System :: OS Independent
Requires-Python: >=3.8
License-File: LICENSE
Requires-Dist: beautifulsoup4==4.13.4
Requires-Dist: blinker==1.4
Requires-Dist: chardet==5.2.0
Requires-Dist: flask==2.0.3
Requires-Dist: mitmproxy==8.0.0
Requires-Dist: openpyxl==3.1.5
Requires-Dist: pandas==2.0.3
Requires-Dist: pika==1.3.2
Requires-Dist: psutil==5.8.0
Requires-Dist: pyotp==2.4.0
Requires-Dist: pytz==2025.2
Requires-Dist: selenium==4.27.1
Requires-Dist: undetected-chromedriver==3.5.5
Requires-Dist: werkzeug==2.0.3
Requires-Dist: xlrd==2.0.2
